nbdev/__init__.py
nbdev/_modidx.py
nbdev/clean.py
nbdev/cli.py
nbdev/config.py
nbdev/diff.py
nbdev/doclinks.py
nbdev/export.py
nbdev/extract_attachments.py
nbdev/frontmatter.py
nbdev/imports.py
nbdev/maker.py
nbdev/merge.py
nbdev/migrate.py
nbdev/process.py
nbdev/processors.py
nbdev/qmd.py
nbdev/quarto.py
nbdev/release.py
nbdev/scrubmagics.py
nbdev/serve.py
nbdev/serve_drv.py
nbdev/showdoc.py
nbdev/sync.py
nbdev/test.py
nbdev-3.0.8.dist-info/licenses/LICENSE
nbdev-3.0.8.dist-info/METADATA
nbdev-3.0.8.dist-info/WHEEL
nbdev-3.0.8.dist-info/entry_points.txt
nbdev-3.0.8.dist-info/top_level.txt
nbdev-3.0.8.dist-info/RECORD
