Metadata-Version: 2.4
Name: nbdev
Version: 3.0.8
Summary: Create delightful software with Jupyter Notebooks
Author-email: "Jeremy Howard and the fast.ai community" <j@fast.ai>
License: Apache-2.0
Project-URL: Repository, https://github.com/AnswerDotAI/nbdev
Project-URL: Documentation, https://nbdev.fast.ai/
Keywords: nbdev,fastai,jupyter,notebook,export
Classifier: Development Status :: 5 - Production/Stable
Classifier: Intended Audience :: Developers
Classifier: Natural Language :: English
Classifier: Programming Language :: Python :: 3
Classifier: Programming Language :: Python :: 3 :: Only
Classifier: License :: OSI Approved :: Apache Software License
Requires-Python: >=3.9
License-File: LICENSE
Requires-Dist: fastcore>=1.12.3
Requires-Dist: execnb>=0.1.12
Requires-Dist: astunparse
Requires-Dist: ghapi>=1.0.3
Requires-Dist: watchdog
Requires-Dist: asttokens
Requires-Dist: setuptools
Requires-Dist: build
Requires-Dist: fastgit
Requires-Dist: pyyaml
Requires-Dist: tomli; python_version < "3.11"
Provides-Extra: dev
Requires-Dist: ipywidgets; extra == "dev"
Requires-Dist: nbdev-numpy; extra == "dev"
Requires-Dist: nbdev-stdlib; extra == "dev"
Requires-Dist: pandas; extra == "dev"
Requires-Dist: matplotlib; extra == "dev"
Requires-Dist: black; extra == "dev"
Requires-Dist: svg.py; extra == "dev"
Requires-Dist: nbclassic; extra == "dev"
Requires-Dist: pysymbol_llm; extra == "dev"
Requires-Dist: llms-txt; extra == "dev"
Requires-Dist: sphinx; extra == "dev"
Requires-Dist: plum-dispatch; extra == "dev"
Dynamic: license-file
